helloworldsyasya.py
helloworldsyasya-0.0.1.dist-info/METADATA
helloworldsyasya-0.0.1.dist-info/WHEEL
helloworldsyasya-0.0.1.dist-info/top_level.txt
helloworldsyasya-0.0.1.dist-info/RECORD
