Metadata-Version: 2.1
Name: helloworldsyasya
Version: 0.0.1
Summary: Say hello!
Home-page: UNKNOWN
Author: Syasya Putri
License: UNKNOWN
Platform: UNKNOWN
Requires-Dist: blessings (~=1.7)
